yaeb/__init__.py
yaeb/base/__init__.py
yaeb/base/bus.py
yaeb/base/events.py
yaeb/base/handlers.py
yaeb/base/registry.py
yaeb/bus.py
yaeb/handlers/__init__.py
yaeb/handlers/recording.py
yaeb/py.typed
yaeb-1.0.0.dist-info/LICENSE
yaeb-1.0.0.dist-info/WHEEL
yaeb-1.0.0.dist-info/METADATA
yaeb-1.0.0.dist-info/RECORD
