Metadata-Version: 2.1
Name: yaeb
Version: 1.0.0
Summary: A simple typed event bus written in pure python
Home-page: https://github.com/WinterCitizen/yaeb
License: MIT
Keywords: event,bus,typed,eventbus
Author: Daniil Fedyaev
Author-email: wintercitizen@outlook.com
Requires-Python: >=3.10,<4.0
Classifier: License :: OSI Approved :: MIT License
Classifier: Operating System :: OS Independent
Classifier: Programming Language :: Python :: 3
Classifier: Programming Language :: Python :: 3.10
Classifier: Programming Language :: Python :: 3
Project-URL: Repository, https://github.com/WinterCitizen/yaeb
